tilepy/__init__.py
tilepy/_version.py
tilepy/version.py
tilepy/include/CampaignDefinition.py
tilepy/include/ObservationScheduler.py
tilepy/include/Observatories.py
tilepy/include/PointingPlotting.py
tilepy/include/PointingTools.py
tilepy/include/RankingObservationTimes.py
tilepy/include/TilingDetermination.py
tilepy/include/__init__.py
tilepy/include/MapManagement/MapReader.py
tilepy/include/MapManagement/SkyMap.py
tilepy/include/MapManagement/__init__.py
tilepy/scripts/PlottingTwoCampaigns.py
tilepy/scripts/Tiling_Observations.py
tilepy/scripts/__init__.py
tilepy/tools/ConvertGalaxyCatalog.py
tilepy/tools/PlotCumulativeCoverage.py
tilepy/tools/VisualizationTools.py
tilepy/tools/__init__.py
tilepy/tools/contour_map_S190512at.py
tilepy/tools/tobeadapted/GW_A_N.py
tilepy/tools/tobeadapted/GW_A_N_S190728q.py
tilepy/tools/tobeadapted/NiceEarthPlot.py
tilepy/tools/tobeadapted/__init__.py
tilepy-2.7.5.dist-info/licenses/LICENSE.rst
tilepy-2.7.5.dist-info/METADATA
tilepy-2.7.5.dist-info/WHEEL
tilepy-2.7.5.dist-info/entry_points.txt
tilepy-2.7.5.dist-info/top_level.txt
tilepy-2.7.5.dist-info/RECORD
