Metadata-Version: 2.4
Name: tilepy
Version: 2.7.5
Summary: Computation of the tiling scheduling of large localization uncertainty region event with multi-wavelength pointing telescopes.
Author-email: "Monica Seglar-Arroyo, Halim Ashkar, Fabian Schussler, Mathieu de Bony" <astro.tilepy@gmail.com>
Maintainer-email: Monica Seglar-Arroyo <mosear2@gmail.com>, Halim Ashkar <halim.ashkar@llr.in2p3.fr>, Fabian Schussler <fabian.schussler@cea.fr>, Mathieu de Bony <mathieu.debony@cea.fr>
License: Copyright (C) 2016-2025, tilepy developers (Monica Seglar-Arroyo, Halim Ashkar, Fabian Schussler, Mathieu de Bony)
Project-URL: repository, https://github.com/astro-transients/tilepy
Project-URL: documentation, https://github.com/astro-transients/tilepy
Classifier: Intended Audience :: Science/Research
Classifier: License :: OSI Approved :: GNU General Public License v3 (GPLv3)
Classifier: Programming Language :: Python :: 3
Classifier: Programming Language :: Python :: 3.9
Classifier: Programming Language :: Python :: 3.10
Classifier: Programming Language :: Python :: 3.12
Classifier: Topic :: Scientific/Engineering :: Astronomy
Classifier: Development Status :: 5 - Production/Stable
Requires-Python: >=3.9
License-File: LICENSE.rst
Requires-Dist: astropy
Requires-Dist: scipy<1.14.0
Requires-Dist: healpy==1.16.2
Requires-Dist: ipython
Requires-Dist: matplotlib<3.9.0
Requires-Dist: MOCpy
Requires-Dist: numpy
Requires-Dist: pandas
Requires-Dist: pytz
Requires-Dist: ephem
Requires-Dist: gdpyc
Requires-Dist: tables
Requires-Dist: fastparquet
Requires-Dist: skyfield
Requires-Dist: mhealpy<0.4,>=0.3.0
Requires-Dist: ligo.skymap>=2.0.0
Requires-Dist: scikit-learn>=1.6.1
Provides-Extra: tests
Requires-Dist: pytest>=7.0; extra == "tests"
Requires-Dist: pytest-cov; extra == "tests"
Requires-Dist: tomli; extra == "tests"
Requires-Dist: nbmake>=1.5.5; extra == "tests"
Provides-Extra: dev
Requires-Dist: setuptools_scm[toml]; extra == "dev"
Requires-Dist: pre-commit>=4.1.0; extra == "dev"
Requires-Dist: flake8>=7.1.2; extra == "dev"
Requires-Dist: black>=25.1.0; extra == "dev"
Provides-Extra: all
Requires-Dist: tilepy[dev,tests]; extra == "all"
Dynamic: license-file
